Workbook
Name 矮人之坚毅: 图表!$B$278
Name 俺寻思能行: 图表!$B$182
Name 暗行者: 图表!$B$164
Name 奥法骑士: 图表!$B$197
Name 暴风龙纹: 图表!$B$293
Name 本命武器: 图表!$B$195
Name 冰封诅咒: 图表!$B$244
Name 不死生物: 图表!$I$2:$I$6
Name 拆迁法术: 图表!$B$266
Name 抄录龙纹: 图表!$B$302
Name 超自然直觉: 图表!$B$80
Name 炽烈爆发: 图表!$B$246
Name 出神入化: 图表!$B$202
Name 畜牧龙纹: 图表!$B$298
Name 穿刺者: 图表!$B$68
Name 穿透与回旋: 图表!$B$110
Name 创生圣言: 图表!$B$47
Name 创造龙纹: 图表!$B$299
Name 大厨: 图表!$B$130
Name 大一统理论: 图表!$B$147
Name 德鲁伊: 图表!$K$24:$K$33
Name 低身之机敏: 图表!$B$284
Name 第二领域: 图表!$B$157
Name 点穴: 图表!$B$186
Name 动作如潮: 图表!$B$103
Name 斗殴高手: 图表!$B$132
Name 毒师: 图表!$B$165
Name 对人立体机动装置: 图表!$B$106
Name 钝击者: 图表!$B$70
Name 盾牌大师: 图表!$B$129
Name 多样眼波射线: 图表!$B$274
Name 额外吟唱: 图表!$B$161
Name 二刀流: 图表!$B$86
Name 法师: 图表!$M$24:$M$36
Name 法术储存: 图表!$B$250
Name 法术穿透: 图表!$B$177
Name 法术对抗大师: 图表!$B$62
Name 法术分裂: 图表!$B$226
Name 法术恒久: 图表!$B$267
Name 法术极效: 图表!$B$227
Name 法术疾发: 图表!$B$234
Name 法术跨域: 图表!$B$253
Name 法术扩展: 图表!$B$237
Name 法术强效: 图表!$B$228
Name 法术射手: 图表!$B$64
Name 法术瞬发: 图表!$B$232
Name 法术速发: 图表!$B$233
Name 法术塑形: 图表!$B$236
Name 法术稳固: 图表!$B$230
Name 法术延时: 图表!$B$229
Name 法术余力: 图表!$B$225
Name 法术专攻: 图表!$B$223
Name 法术追踪: 图表!$B$231
Name 奋力冲刺: 图表!$B$52
Name 风浪射手: 图表!$B$118
Name 封锁记忆: 图表!$B$257
Name 否决神力: 图表!$B$290
Name 弗莱格索斯之焰: 图表!$B$281
Name 浮光掠影: 图表!$B$107
Name 钢铁坐骑: 图表!$B$169

Sheet 角色
A1: 角色
A2: 浅绿色方格，为公式自动计算。浅蓝色方格，为下拉框式选择。白色方格，必须自行填写。灰色方格，可以自行修改其中的描述名称，也可以不改。
B3: 角色名 | R3: 背景
B4: 玩家名 | R4: 阵营
R5: 信仰
B6: 生物类型 | J6: 体型 | R6: 特点
B7: 种族 | J7: 性别 | R7: 理想
B8: 亚种 | J8: 年龄 | R8: 牵绊
R9: 缺点
B10: 角色外貌描述 | R10: 技能熟练项
R11: 语言
R12: 故事
B15: 角色形象图片

Sheet 主要情况
A1: 主要情况
A2: 浅绿色方格，为公式自动计算。浅蓝色方格，为下拉框式选择。白色方格，必须自行填写。灰色方格，可以自行修改其中的描述名称，也可以不改。
A3: 属性 | J3: 职业 | AD3: 种族 | AZ3: 资源消耗记录
D4: 属性值 | E4: 调整值 | F4: 豁免熟练 | G4: 豁免修正 | H4: 豁免总值 | J4: 总等级 | M4: =SUM(W7:Z10) -> 0 | R4: 熟练 加值 | V4: =MAX(INT((M4+7)/4)+Y5,2) -> 2 | Y4: 修正 | AD4: 特性 | AH4: 效果 | AZ4: 名称 | BC4: 当前值 | BF4: 最大值 | BI4: 恢复
A5: 力量 | E5: =INT(D5/2-5) -> -5 | F5: 无 | H5: =E5+G5+IF(F5="有",V4,0) -> -5 | AD5: 生物类型 | BE5: /
J6: 职业与兼职 | R6: 子职业 | W6: 等级 | AD6: 属性值提升 | BE6: /
A7: 敏捷 | E7: =INT(D7/2-5) -> -5 | F7: 无 | H7: =E7+G7+IF(F7="有",V4,0) -> -5 | J7: 初始职业 | AD7: 体型 | BE7: /
J8: 兼职一 | BE8: /
A9: 体质 | E9: =INT(D9/2-5) -> -5 | F9: 无 | H9: =E9+G9+IF(F9="有",V4,0) -> -5 | J9: 兼职二 | BE9: /
J10: 兼职三 | BE10: /
A11: 智力 | E11: =INT(D11/2-5) -> -5 | F11: 无 | H11: =E11+G11+IF(F11="有",V4,0) -> -5 | M11: 当前值 | R11: 最大值 | V11: 生命上限修正 | BE11: /
J12: 生命值 | Q12: / | R12: =图表!B21+V12 -> 0 | BE12: /
A13: 感知 | E13: =INT(D13/2-5) -> -5 | F13: 无 | H13: =E13+G13+IF(F13="有",V4,0) -> -5 | V13: 临时生命值 | BE13: /
J14: 生命骰数量 | M14: 1 | Q14: / | R14: =M4 -> 0 | AD14: 语言 | BE14: /
A16: 技能 | H16: 战斗数据 | AD16: 专长 | AZ16: 状态记录
A17: 力量系 | D17: 技能熟练 | E17: 技能修正 | F17: 技能总值 | I17: 先攻熟练 | M17: 先攻修正 | Q17: 先攻总值 | AD17: 等级 | AF17: 名称 | AJ17: 效果 | AU17: 可选项说明 | AZ17: 在此记录你具有的增益效果、不利影响。
A18: 运动 | D18: 无 | F18: =E5+E18+IF(D18="熟练",V4,0)+IF(D18="专精",V4*2,0)+IF(D18="万事通",INT(V4/2),0) -> -5 | H18: 先攻 | I18: 无 | Q18: =E7+M18+IF(I18="熟练",V4,0)+IF(I18="万事通",INT(V4/2),0) -> -5 | AD18: 1
A19: 威吓 | D19: 无 | F19: =E5+E19+IF(D19="熟练",V4,0)+IF(D19="专精",V4*2,0)+IF(D19="万事通",INT(V4/2),0) -> -5 | H19: 防具 | I19: 防具类型 | M19: 装备加值 | Q19: AC值 | V19: 其它修正 | Y19: AC总值 | AD19: 1
A20: 敏捷系 | D20: 技能熟练 | E20: 技能修正 | F20: 技能总值 | H20: 盔甲 | M20: 0 | Q20: =M20+V4+IF(I20="无盔甲",8+E7,0)+IF(I20="镶钉皮甲",10+E7)+IF(I20="半身板甲",13+MIN(E7,2),0)+IF(I20="板甲",16,0)+IF(I20="法师护甲",11+E7,0)+IF(AND(I20="武僧无甲防御",I21="无盾牌"),8+E7+E13,0)+IF(I20="狂战士无甲防御",8+E7+E9,0) -> 2 | Y20: =Q20+Q21+V20 -> 2 | AD20: 3
A21: 体操 | D21: 无 | F21: =E7+E21+IF(D21="熟练",V4,0)+IF(D21="专精",V4*2,0)+IF(D21="万事通",INT(V4/2),0) -> -5 | H21: 盾牌 | Q21: =(M21*IF(I21="有盾牌",1,0)+IF(I21="有盾牌",2,0)) -> 0 | AD21: 6
A22: 巧手 | D22: 无 | F22: =E7+E22+IF(D22="熟练",V4,0)+IF(D22="专精",V4*2,0)+IF(D22="万事通",INT(V4/2),0) -> -5 | H22: 攻击 | I22: 攻击类型 | M22: 装备加值 | Q22: 关联属性 | V22: 其它修正 | Y22: 命中总值 | AD22: 9
A23: 隐匿 | D23: 无 | F23: =E7+E23+IF(D23="熟练",V4,0)+IF(D23="专精",V4*2,0)+IF(D23="万事通",INT(V4/2),0) -> -5 | H23: 主武器 | M23: 0 | Q23: 力量 | Y23: =V4+M23+V23+IF(Q23="力量",E5,0)+IF(Q23="敏捷",E7,0)+IF(Q23="体质",E9,0)+IF(Q23="智力",E11,0)+IF(Q23="感知",E13,0) -> -3 | AD23: 12
A24: 智力系 | D24: 技能熟练 | E24: 技能修正 | F24: 技能总值 | H24: 副武器 | M24: 0 | Q24: 敏捷 | Y24: =V4+M24+V24+IF(Q24="力量",E5,0)+IF(Q24="敏捷",E7,0)+IF(Q24="体质",E9,0)+IF(Q24="智力",E11,0)+IF(Q24="感知",E13,0) -> -3 | AD24: 15
A25: 奥秘 | D25: 无 | F25: =E11+E25+IF(D25="熟练",V4,0)+IF(D25="专精",V4*2,0)+IF(D25="万事通",INT(V4/2),0) -> -5 | H25: 法术攻击 | M25: 0 | Q25: 感知 | Y25: =V4+M25+V25+IF(Q25="力量",E5,0)+IF(Q25="敏捷",E7,0)+IF(Q25="体质",E9,0)+IF(Q25="智力",E11,0)+IF(Q25="感知",E13,0) -> -3 | AD25: 18
A26: 灵能 | D26: 无 | F26: =E11+E26+IF(D26="熟练",V4,0)+IF(D26="专精",V4*2,0)+IF(D26="万事通",INT(V4/2),0) -> -5 | H26: 豁免 | I26: 豁免来源 | M26: 装备加值 | Q26: 关联属性 | V26: 其它修正 | Y26: 豁免DC
A27: 宗教 | D27: 无 | F27: =E11+E27+IF(D27="熟练",V4,0)+IF(D27="专精",V4*2,0)+IF(D27="万事通",INT(V4/2),0) -> -5 | H27: 法术 | M27: 0 | Q27: 感知 | Y27: =8+V4+M27+V27+IF(Q27="力量",E5,0)+IF(Q27="敏捷",E7,0)+IF(Q27="体质",E9,0)+IF(Q27="智力",E11,0)+IF(Q27="感知",E13,0) -> 5
A28: 历史 | D28: 无 | F28: =E11+E28+IF(D28="熟练",V4,0)+IF(D28="专精",V4*2,0)+IF(D28="万事通",INT(V4/2),0) -> -5 | H28: 非法术 | M28: 0 | Q28: 力量 | Y28: =8+V4+M28+V28+IF(Q28="力量",E5,0)+IF(Q28="敏捷",E7,0)+IF(Q28="体质",E9,0)+IF(Q28="智力",E11,0)+IF(Q28="感知",E13,0) -> 5
A29: 自然 | D29: 无 | F29: =E11+E29+IF(D29="熟练",V4,0)+IF(D29="专精",V4*2,0)+IF(D29="万事通",INT(V4/2),0) -> -5 | H29: 速度 | I29: 种族基本速度 | M29: 力量加成 | Q29: 其它修正 | V29: 最终速度 | AD29: 装备熟练项
A30: 调查 | D30: 无 | F30: =E11+E30+IF(D30="熟练",V4,0)+IF(D30="专精",V4*2,0)+IF(D30="万事通",INT(V4/2),0) -> -5 | H30: 步行速度 | I30: 30 | M30: =5*E5 -> -25 | V30: =SUM(I30:U30) -> 5 | Y30: 尺 | AD30: 非异种武器 | AH30: 简易武器
A31: 表演 | D31: 无 | F31: =E11+E31+IF(D31="熟练",V4,0)+IF(D31="专精",V4*2,0)+IF(D31="万事通",INT(V4/2),0) -> -5 | H31: 其它速度 | I31: 飞行，游泳，攀爬，掘地 | Y31: 尺 | AD31: 异种武器 | AH31: 无
A32: 感知系 | D32: 技能熟练 | E32: 技能修正 | F32: 技能总值 | H32: 伤害抵抗 | AD32: 防具 | AH32: 无
A33: 察觉 | D33: 无 | F33: =E13+E33+IF(D33="熟练",V4,0)+IF(D33="专精",V4*2,0)+IF(D33="万事通",INT(V4/2),0) -> -5 | H33: 伤害抗性 | AD33: 配件 | AH33: 无
A34: 洞悉 | D34: 无 | F34: =E13+E34+IF(D34="熟练",V4,0)+IF(D34="专精",V4*2,0)+IF(D34="万事通",INT(V4/2),0) -> -5 | H34: 伤害免疫
A35: 医药 | D35: 无 | F35: =E13+E35+IF(D35="熟练",V4,0)+IF(D35="专精",V4*2,0)+IF(D35="万事通",INT(V4/2),0) -> -5 | H35: 伤害吸收 | AD35: 常用掷骰指令
A36: 生存 | D36: 无 | F36: =E13+E36+IF(D36="熟练",V4,0)+IF(D36="专精",V4*2,0)+IF(D36="万事通",INT(V4/2),0) -> -5 | H36: 伤害易伤 | AD36: 巨剑伤害
A37: 驯兽 | D37: 无 | F37: =E13+E37+IF(D37="熟练",V4,0)+IF(D37="专精",V4*2,0)+IF(D37="万事通",INT(V4/2),0) -> -5 | H37: 状态抵抗 | AD37: 先攻
A38: 游说 | D38: 无 | F38: =E13+E38+IF(D38="熟练",V4,0)+IF(D38="专精",V4*2,0)+IF(D38="万事通",INT(V4/2),0) -> -5 | H38: 豁免优势 | AD38: 火球术
A39: 欺瞒 | D39: 无 | F39: =E13+E39+IF(D39="熟练",V4,0)+IF(D39="专精",V4*2,0)+IF(D39="万事通",INT(V4/2),0) -> -5 | H39: 状态免疫 | AD39: 专注豁免

Sheet 职业特性
A1: 职业特性
I2: 初始职业 | L2: =主要情况!M7 -> 0 | AJ2: 子职业 | AM2: =主要情况!R7 -> 0
A3: 等级 | C3: 特性 | AA3: 等级 | AC3: 特性
A4: 1 | AA4: 1
A5: 2
A6: 3
A7: 4
A8: 5
A9: 6
A10: 7
A11: 8
A12: 9 | AJ12: 职业特色选项 | AM12: 魔能祈唤
A13: 10 | AA13: 等级 | AC13: 特性
A14: 11
A15: 12
A16: 13
A17: 14
A18: 15
A19: 16
A20: 17
A21: 18
A22: 19
A23: 20
I28: 兼职一 | L28: =主要情况!M8 -> 0 | AJ28: 子职业 | AM28: =主要情况!R8 -> 0
A29: 等级 | C29: 特性 | AA29: 等级 | AC29: 特性
A30: 1 | AA30: 1
A31: 2
A32: 3
A33: 4
A34: 5
A35: 6
A36: 7
A37: 8
A38: 9 | AJ38: 职业特色选项 | AM38: 制造物品
A39: 10 | AA39: 等级 | AC39: 特性
A40: 11
A41: 12
A42: 13
A43: 14
A44: 15
A45: 16
A46: 17
A47: 18
A48: 19
A49: 20
I54: 兼职二 | L54: =主要情况!M9 -> 0 | AJ54: 子职业 | AM54: =主要情况!R9 -> 0
A55: 等级 | C55: 特性 | AA55: 等级 | AC55: 特性
A56: 1 | C56: 施法 | AA56: 1
A57: 2
A58: 3
A59: 4
A60: 5
A61: 6
A62: 7
A63: 8
A64: 9 | AJ64: 职业特色选项 | AM64: 法术风格
A65: 10 | AA65: 等级 | AC65: 特性
A66: 11
A67: 12
A68: 13
A69: 14
A70: 15
A71: 16
A72: 17
A73: 18
A74: 19
A75: 20
I80: 兼职三 | L80: =主要情况!M10 -> 0 | AJ80: 子职业 | AM80: =主要情况!R10 -> 0
A81: 等级 | C81: 特性 | AA81: 等级 | AC81: 特性
A82: 1 | C82: 施法 | AA82: 1
A83: 2
A84: 3
A85: 4
A86: 5
A87: 6
A88: 7
A89: 8
A90: 9 | AJ90: 职业特色选项 | AM90: 战斗风格
A91: 10 | AA91: 等级 | AC91: 特性
A92: 11
A93: 12
A94: 13
A95: 14
A96: 15
A97: 16
A98: 17
A99: 18
A100: 19
A101: 20

Sheet 装备
A1: 装备
A3: 非魔法物品 | AC3: 魔法物品
A4: 名称 | E4: 特殊 | G4: 描述 | S4: 单价 | X4: 数量 | AC4: 名称 | AG4: 同调 | AI4: 描述 | AW4: 单价 | BB4: 数量
S5: =IF($A5<>0,IF($E5<>0,VLOOKUP($E5,图表!$A$306:$C$317,3,0)+VLOOKUP($A5,图表!$A$330:$C$475,3,0),VLOOKUP($A5,图表!$A$330:$C$475,3,0)),"") | V5: gp× | AG5: =IF($AC5<>0,VLOOKUP($AC5,图表!$E$330:$H$1139,2,0),"") | AW5: =IF($AC5<>0,VLOOKUP($AC5,图表!$E$330:$H$1139,4,0),"") | AZ5: gp× | CB5: =IF(S5<>"",S5*X5,"") | CC5: =IF(AW5<>"",AW5*BB5,"")
S6: =IF($A6<>0,IF($E6<>0,VLOOKUP($E6,图表!$A$306:$C$317,3,0)+VLOOKUP($A6,图表!$A$330:$C$475,3,0),VLOOKUP($A6,图表!$A$330:$C$475,3,0)),"") | V6: gp× | AG6: =IF($AC6<>0,VLOOKUP($AC6,图表!$E$330:$H$1139,2,0),"") | AW6: =IF($AC6<>0,VLOOKUP($AC6,图表!$E$330:$H$1139,4,0),"") | AZ6: gp× | CB6: =IF(S6<>"",S6*X6,"") | CC6: =IF(AW6<>"",AW6*BB6,"")
S7: =IF($A7<>0,IF($E7<>0,VLOOKUP($E7,图表!$A$306:$C$317,3,0)+VLOOKUP($A7,图表!$A$330:$C$475,3,0),VLOOKUP($A7,图表!$A$330:$C$475,3,0)),"") | V7: gp× | AG7: =IF($AC7<>0,VLOOKUP($AC7,图表!$E$330:$H$1139,2,0),"") | AW7: =IF($AC7<>0,VLOOKUP($AC7,图表!$E$330:$H$1139,4,0),"") | AZ7: gp× | CB7: =IF(S7<>"",S7*X7,"") | CC7: =IF(AW7<>"",AW7*BB7,"")
S8: =IF($A8<>0,IF($E8<>0,VLOOKUP($E8,图表!$A$306:$C$317,3,0)+VLOOKUP($A8,图表!$A$330:$C$475,3,0),VLOOKUP($A8,图表!$A$330:$C$475,3,0)),"") | V8: gp× | AG8: =IF($AC8<>0,VLOOKUP($AC8,图表!$E$330:$H$1139,2,0),"") | AW8: =IF($AC8<>0,VLOOKUP($AC8,图表!$E$330:$H$1139,4,0),"") | AZ8: gp× | CB8: =IF(S8<>"",S8*X8,"") | CC8: =IF(AW8<>"",AW8*BB8,"")
S9: =IF($A9<>0,IF($E9<>0,VLOOKUP($E9,图表!$A$306:$C$317,3,0)+VLOOKUP($A9,图表!$A$330:$C$475,3,0),VLOOKUP($A9,图表!$A$330:$C$475,3,0)),"") | V9: gp× | AG9: =IF($AC9<>0,VLOOKUP($AC9,图表!$E$330:$H$1139,2,0),"") | AW9: =IF($AC9<>0,VLOOKUP($AC9,图表!$E$330:$H$1139,4,0),"") | AZ9: gp× | CB9: =IF(S9<>"",S9*X9,"") | CC9: =IF(AW9<>"",AW9*BB9,"")
S10: =IF($A10<>0,IF($E10<>0,VLOOKUP($E10,图表!$A$306:$C$317,3,0)+VLOOKUP($A10,图表!$A$330:$C$475,3,0),VLOOKUP($A10,图表!$A$330:$C$475,3,0)),"") | V10: gp× | AG10: =IF($AC10<>0,VLOOKUP($AC10,图表!$E$330:$H$1139,2,0),"") | AW10: =IF($AC10<>0,VLOOKUP($AC10,图表!$E$330:$H$1139,4,0),"") | AZ10: gp× | CB10: =IF(S10<>"",S10*X10,"") | CC10: =IF(AW10<>"",AW10*BB10,"")
S11: =IF($A11<>0,IF($E11<>0,VLOOKUP($E11,图表!$A$306:$C$317,3,0)+VLOOKUP($A11,图表!$A$330:$C$475,3,0),VLOOKUP($A11,图表!$A$330:$C$475,3,0)),"") | V11: gp× | AG11: =IF($AC11<>0,VLOOKUP($AC11,图表!$E$330:$H$1139,2,0),"") | AW11: =IF($AC11<>0,VLOOKUP($AC11,图表!$E$330:$H$1139,4,0),"") | AZ11: gp× | CB11: =IF(S11<>"",S11*X11,"") | CC11: =IF(AW11<>"",AW11*BB11,"")
S12: =IF($A12<>0,IF($E12<>0,VLOOKUP($E12,图表!$A$306:$C$317,3,0)+VLOOKUP($A12,图表!$A$330:$C$475,3,0),VLOOKUP($A12,图表!$A$330:$C$475,3,0)),"") | V12: gp× | AG12: =IF($AC12<>0,VLOOKUP($AC12,图表!$E$330:$H$1139,2,0),"") | AW12: =IF($AC12<>0,VLOOKUP($AC12,图表!$E$330:$H$1139,4,0),"") | AZ12: gp× | CB12: =IF(S12<>"",S12*X12,"") | CC12: =IF(AW12<>"",AW12*BB12,"")
S13: =IF($A13<>0,IF($E13<>0,VLOOKUP($E13,图表!$A$306:$C$317,3,0)+VLOOKUP($A13,图表!$A$330:$C$475,3,0),VLOOKUP($A13,图表!$A$330:$C$475,3,0)),"") | V13: gp× | AG13: =IF($AC13<>0,VLOOKUP($AC13,图表!$E$330:$H$1139,2,0),"") | AW13: =IF($AC13<>0,VLOOKUP($AC13,图表!$E$330:$H$1139,4,0),"") | AZ13: gp× | CB13: =IF(S13<>"",S13*X13,"") | CC13: =IF(AW13<>"",AW13*BB13,"")
S14: =IF($A14<>0,IF($E14<>0,VLOOKUP($E14,图表!$A$306:$C$317,3,0)+VLOOKUP($A14,图表!$A$330:$C$475,3,0),VLOOKUP($A14,图表!$A$330:$C$475,3,0)),"") | V14: gp× | AG14: =IF($AC14<>0,VLOOKUP($AC14,图表!$E$330:$H$1139,2,0),"") | AW14: =IF($AC14<>0,VLOOKUP($AC14,图表!$E$330:$H$1139,4,0),"") | AZ14: gp× | CB14: =IF(S14<>"",S14*X14,"") | CC14: =IF(AW14<>"",AW14*BB14,"")
S15: =IF($A15<>0,IF($E15<>0,VLOOKUP($E15,图表!$A$306:$C$317,3,0)+VLOOKUP($A15,图表!$A$330:$C$475,3,0),VLOOKUP($A15,图表!$A$330:$C$475,3,0)),"") | V15: gp× | AG15: =IF($AC15<>0,VLOOKUP($AC15,图表!$E$330:$H$1139,2,0),"") | AW15: =IF($AC15<>0,VLOOKUP($AC15,图表!$E$330:$H$1139,4,0),"") | AZ15: gp× | CB15: =IF(S15<>"",S15*X15,"") | CC15: =IF(AW15<>"",AW15*BB15,"")
S16: =IF($A16<>0,IF($E16<>0,VLOOKUP($E16,图表!$A$306:$C$317,3,0)+VLOOKUP($A16,图表!$A$330:$C$475,3,0),VLOOKUP($A16,图表!$A$330:$C$475,3,0)),"") | V16: gp× | AG16: =IF($AC16<>0,VLOOKUP($AC16,图表!$E$330:$H$1139,2,0),"") | AW16: =IF($AC16<>0,VLOOKUP($AC16,图表!$E$330:$H$1139,4,0),"") | AZ16: gp× | CB16: =IF(S16<>"",S16*X16,"") | CC16: =IF(AW16<>"",AW16*BB16,"")
... S25: =IF($A25<>0,IF($E25<>0,VLOOKUP($E25,图表!$A$306:$C$317,3,0)+VLOOKUP($A25,图表!$A$330:$C$475,3,0),VLOOKUP($A25,图表!$A$330:$C$475,3,0)),"") | V25: gp× | AG25: =IF($AC25<>0,VLOOKUP($AC25,图表!$E$330:$H$1139,2,0),"") | AW25: =IF($AC25<>0,VLOOKUP($AC25,图表!$E$330:$H$1139,4,0),"") | AZ25: gp× | CB25: =IF(S25<>"",S25*X25,"") | CC25: =IF(AW25<>"",AW25*BB25,"")
A26: 负重 | AC26: 购物
A27: 有力体型 | G27: 无有力体型 | AC27: 魔法物品总开销 | AI27: =SUM(CC5:CC25) -> 0 | AS27: gp
A28: 负重能力 | G28: =图表!T73 -> #N/A | Q28: 磅 | AC28: 非魔法物品总开销 | AI28: =SUM(CB5:CB25) -> 0 | AS28: gp | AV28: 同调总数 | AZ28: =COUNTIF(AG5:AH25,"是") -> 0 | BB28: 件
A29: 装备总重 | Q29: 磅 | AC29: 初始资金 | AI29: 999999 | AS29: gp
A30: 是否超载 | G30: =IF(G29>G28,"超载","未超载") -> #N/A | AC30: 剩余资金 | AI30: =AI29-AI27-AI28 -> 999999 | AS30: gp

Sheet 法术
A1: 法术
A2: 关联属性 | E2: =主要情况!Q27 -> 感知 | I2: 法术豁免DC | N2: =主要情况!Y27 -> 5 | R2: 可用环法数量 | W2: 准备法术 | AD2: 个 | AF2: 施法者等级 | AJ2: 14 | AL2: 级 | AN2: 环阶 | AP2: 施法者法术位 | AV2: 环阶 | AX2: 契约魔法
A3: 法术类型 | E3: =主要情况!I27 -> 0 | I3: 法术攻击加值 | N3: =主要情况!Y25 -> -3 | R3: 已知戏法 | Z3: 个 | AF3: 契术师等级 | AJ3: 15 | AL3: 级 | AN3: 0 | AP3: ∞ | AV3: 0 | AX3: ∞
A4: 法术 | E4: 环阶 | G4: 法术详述 | AL4: 来源 | AN4: 1 | AP4: 0 | AR4: / | AS4: =IF(AJ2>5,6,IF(AJ2>3,5,IF(AJ2>1,4,IF(AJ2>0,3,0)))) -> 6 | AV4: 1 | AX4: 0 | AZ4: / | BA4: =IF(AJ3=2,2,IF(AJ3=1,1,0)) -> 0
AN5: 2 | AP5: 0 | AR5: / | AS5: =IF(AJ2>15,6,IF(AJ2>11,5,IF(AJ2>7,4,IF(AJ2>3,3,IF(AJ2>2,2,0))))) -> 5 | AV5: 2 | AX5: 0 | AZ5: / | BA5: =IF(OR(AJ3=3,AJ3=4),2,0) -> 0
AN6: 3 | AP6: 0 | AR6: / | AS6: =IF(AJ2>17,6,IF(AJ2>13,5,IF(AJ2>9,4,IF(AJ2>5,3,IF(AJ2>4,2,0))))) -> 5 | AV6: 3 | AX6: 0 | AZ6: / | BA6: =IF(OR(AJ3=5,AJ3=6),2,0) -> 0
AN7: 4 | AP7: 0 | AR7: / | AS7: =IF(AJ2>19,6,IF(AJ2>16,5,IF(AJ2>12,4,IF(AJ2>8,3,IF(AJ2>7,2,IF(AJ2>6,1,0)))))) -> 4 | AV7: 4 | AX7: 0 | AZ7: / | BA7: =IF(OR(AJ3=7,AJ3=8),3,0) -> 0
AN8: 5 | AP8: 0 | AR8: / | AS8: =IF(AJ2>20,6,IF(AJ2>19,5,IF(AJ2>16,4,IF(AJ2>12,3,IF(AJ2>9,2,IF(AJ2>8,1,0)))))) -> 3 | AV8: 5 | AX8: 0 | AZ8: / | BA8: =IF(OR(AJ3=9,AJ3=10,AJ3=11),3,IF(OR(AJ3=12,AJ3=13,AJ3=14,AJ3=15,AJ3=16),4,IF(OR(AJ3=17,AJ3=18,AJ3=19,AJ3=20),5,0))) -> 4
AN9: 6 | AP9: 0 | AR9: / | AS9: =IF(AJ2>20,6,IF(AJ2>19,5,IF(AJ2>18,4,IF(AJ2>14,3,IF(AJ2>11,2,IF(AJ2>10,1,0)))))) -> 2 | AV9: 6 | AX9: 无 | AZ9: / | BA9: =IF(AJ3>10,"玄奥","无") -> 玄奥
AN10: 7 | AP10: 0 | AR10: / | AS10: =IF(AJ2>21,6,IF(AJ2>20,5,IF(AJ2>19,4,IF(AJ2>16,3,IF(AJ2>13,2,IF(AJ2>12,1,0)))))) -> 2 | AV10: 7 | AX10: 无 | AZ10: / | BA10: =IF(AJ3>12,"玄奥","无") -> 玄奥
AN11: 8 | AP11: 0 | AR11: / | AS11: =IF(AJ2>21,5,IF(AJ2>20,4,IF(AJ2>18,3,IF(AJ2>15,2,IF(AJ2>14,1,0))))) -> 0 | AV11: 8 | AX11: 无 | AZ11: / | BA11: =IF(AJ3>14,"玄奥","无") -> 玄奥
AN12: 9 | AP12: 0 | AR12: / | AS12: =IF(AJ2>21,3,IF(AJ2>18,2,IF(AJ2>16,1,0))) -> 0 | AV12: 9 | AX12: 无 | AZ12: / | BA12: =IF(AJ3>16,"玄奥","无") -> 无
AS13: 当前值 | AW13: 最大值
AN14: 术法点 | AV14: / | AZ14: 点

Sheet 战技
A1: 战技
A2: 关联属性 | E2: =主要情况!Q28 -> 力量 | I2: 豁免DC | M2: =主要情况!Y28 -> 5 | S2: 准备战技 | X2: =+IF(E2="力量",主要情况!E5,0)+IF(E2="敏捷",主要情况!E7,0)+IF(E2="体质",主要情况!E9,0)+IF(E2="智力",主要情况!E11,0)+IF(E2="感知",主要情况!E13,0) -> -5 | AA2: 个 | AC2: 流派 | AH2: 摘星流 | AS2: 当前值 | AW2: 最大值
A3: 战技 | E3: 级别 | G3: 战技详述 | AN3: 卓越骰数量 | AV3: / | AZ3: 枚
AN4: 卓越骰大小 | AS4: d4

Sheet 怪物
A1: 怪物资料
A3: 参考怪物资料 | AE3: 最终怪物资料
A4: 将《怪物图鉴》上的怪物初始数据填写在这里 | AE4: 将经过部署强化、购买装备、变形结合等方法修改之后的，部署数据或变形数据，写在这里。
Y6: 部署或变形
Y7: 常驻变形
Y8: 获取方法
Y9: 完全变形术

Sheet 图表
A1: 职业 | B1: 期望生命 | C1: 首级额外生命 | E1: 类人生物 | F1: 巨人 | G1: 精类 | H1: 构装生物 | I1: 不死生物 | J1: 天界生物 | K1: 邪魔 | L1: 植物 | M1: 元素 | N1: 泥怪 | O1: 异怪 | P1: 龙 | Q1: 怪兽 | R1: 野兽 | T1: 属性值 | U1: 花费点数
A2: 狂战士 | B2: 7 | C2: 5 | E2: 定制血统 | F2: 定制血统 | G2: 定制血统 | H2: 定制血统 | I2: 定制血统 | J2: 定制血统 | K2: 定制血统 | L2: 定制血统 | M2: 定制血统 | N2: 定制血统 | O2: 定制血统 | P2: 定制血统 | Q2: 定制血统 | R2: 定制血统 | T2: 8 | U2: 0
A3: 圣武士 | B3: 6 | C3: 4 | E3: 人类 | F3: 歌利亚 | G3: 仙灵 | H3: 机关人 | I3: 剪影 | J3: 阿斯莫 | K3: 提夫林 | L3: 古树 | M3: 元素裔 | N3: 流浆体 | O3: 呋噜 | P3: 狗头人 | Q3: 人马 | T3: 9 | U3: 1
A4: 游侠 | B4: 6 | C4: 4 | E4: 精灵 | F4: 独眼巨人 | G4: 兔人 | H4: 仿生人 | I4: 修罗 | J4: 半梦灵 | K4: 地狱之子 | L4: 蕈人 | M4: 小巨灵 | N4: 生化之雪 | O4: 眼魔 | P4: 真龙 | Q4: 原体蛇人 | T4: 10 | U4: 2
A5: 武僧 | B5: 5 | C5: 3 | E5: 矮人 | G5: 半羊人 | H5: 稻草人 | I5: 血族 | J5: 福瑞天族 | K5: 欲魔 | L5: 阿娜温 | O5: 厄兰 | Q5: 牛头人 | T5: 11 | U5: 3
A6: 灵能武士 | B6: 6 | C6: 4 | E6: 侏儒 | G6: 天狗 | H6: 自动侏儒 | I6: 重生者 | Q6: 狮人 | T6: 12 | U6: 4
A7: 游荡者 | B7: 5 | C7: 3 | E7: 半身人 | G7: 幻身灵 | Q7: 螳螂人 | T7: 13 | U7: 5
A8: 奇械师 | B8: 5 | C8: 3 | E8: 兽人 | G8: 狐妖 | Q8: 象人 | T8: 14 | U8: 7
A9: 契术师 | B9: 5 | C9: 3 | E9: 化兽者 | G9: 巫咒之子 | Q9: 鼯猴人 | T9: 15 | U9: 9
A10: 吟游诗人 | B10: 5 | C10: 3 | E10: 吉斯人 | T10: 16 | U10: 12
A11: 牧师 | B11: 5 | C11: 3 | E11: 地精
A12: 德鲁伊 | B12: 5 | C12: 3 | E12: 猫人
A13: 灵能师 | B13: 4 | C13: 2 | E13: 维多肯
A14: 法师 | B14: 4 | C14: 2 | E14: 蜥蜴人
E15: 龟人
A16: 初始职业生命值 | B16: =IFERROR(VLOOKUP(主要情况!M7,A2:C14,2,0)*主要情况!W7+VLOOKUP(主要情况!M7,A2:C14,3,0),0) -> 0 | E16: 鹰人
A17: 兼职一生命值 | B17: =IFERROR(VLOOKUP(主要情况!M8,A2:C14,2,0)*主要情况!W8,0) -> 0 | E17: 鱼人
A18: 兼职二生命值 | B18: =IFERROR(VLOOKUP(主要情况!M9,A2:C14,2,0)*主要情况!W9,0) -> 0
A19: 兼职三生命值 | B19: =IFERROR(VLOOKUP(主要情况!M10,A2:C14,2,0)*主要情况!W10,0) -> 0
A21: 总生命值 | B21: =SUM(B16:B19)+主要情况!E9*主要情况!M4 -> 0
A23: 狂战士子职业 | B23: 圣武士子职业 | C23: 游侠子职业 | D23: 武僧子职业 | E23: 灵能武士子职业 | F23: 游荡者子职业 | G23: 奇械师子职业 | H23: 契术师子职业 | I23: 吟游诗人子职业 | J23: 牧师子职业 | K23: 德鲁伊子职业 | L23: 灵能师子职业 | M23: 法师子职业
A24: 图腾武者 | B24: 奉献之誓 | C24: 狩魔猎人 | D24: 散打宗 | E24: 风物行者 | F24: 刺客 | G24: 构造铁匠 | H24: 邪魔 | I24: 轶闻学院 | J24: 生命领域 | K24: 大地结社 | L24: 创形修会 | M24: 防护学派
A25: 先祖守卫 | B25: 古贤之誓 | C25: 魔射手 | D25: 暗影宗 | E25: 回音骑士 | F25: 斥候 | G25: 魔炮专家 | H25: 至高妖精 | I25: 偶像学院 | J25: 死亡领域 | K25: 月亮结社 | L25: 惑心修会 | M25: 变化学派
A26: 狂热者 | B26: 复仇之誓 | C26: 兽王 | D26: 四象宗 | E26: 守卫铁卫 | F26: 诡术师 | G26: 装甲师 | H26: 旧日支配者 | I26: 勇气学院 | J26: 和平领域 | K26: 星辰结社 | L26: 旅行修会 | M26: 咒法学派
A27: 巨人 | B27: 救赎之誓 | C27: 龙兽守卫 | D27: 日魂宗 | E27: 原力大师 | F27: 策士 | G27: 炼金师 | H27: 咒剑 | I27: 剑舞学院 | J27: 战争领域 | K27: 牧人结社 | L27: 洞察修会 | M27: 幻术学派
A28: 自然先驱 | B28: 守望之誓 | C28: 士官长 | D28: 命流宗 | E28: 魂刃主宰 | F28: 鬼魅 | G28: 神枪手 | H28: 死灵 | I28: 低语学院 | J28: 光明领域 | K28: 孢子结社 | L28: 百变修会 | M28: 死灵学派
A29: 狂野魔法 | B29: 荣耀之誓 | C29: 边界行者 | D29: 剑圣宗 | F29: 游荡剑客 | G29: 机车士 | H29: 巨灵 | I29: 创造学院 | J29: 幽暗领域 | K29: 梦境结社 | L29: 能量修会 | M29: 预言学派
A30: 野兽 | B30: 王冠之誓 | C30: 幽域追踪者 | D30: 星我宗 | F30: 役虫者 | G30: 科学怪人 | H30: 深海意志 | I30: 灵魂学院 | J30: 律法领域 | K30: 野火结社 | M30: 附魔学派
A31: 鲜血 | B31: 破晓之誓 | C31: 妖精漫游者 | D31: 神龙宗 | F31: 自由之翼 | H31: 灵契师 | J31: 狂野领域 | K31: 风暴结社 | M31: 塑能学派
B32: 飨食之誓 | C32: 海洋保护者 | D32: 酒仙宗 | J32: 奥秘领域 | K32: 凛冬结社 | M32: 书士会
B33: 月剑之誓 | C33: 剧毒杀手 | J33: 心灵领域 | K33: 牧位者 | M33: 符咒女巫
B34: 玫瑰之誓 | J34: 剑舞领域 | M34: 幽影魔法
J35: 时间领域 | M35: 时间魔法
M36: 重力魔法
A38: 专长名称 | B38: 专长效果
A39: 雾隐之力 | B39: 迷雾隐藏了你的人物的一部分记忆。随着时间流逝，越来越多的遗失记忆回到了你身上，这也许会在特定的时候帮助你。 该专长没有帮助角色扮演之外的效果。然而，在游戏进行的任何时段，你可以在长休完成后，把这个专长转变成另一个你能选取的、并且符合你人物背景的专长。这表现为你在睡梦中恢复了经验技术。 雾隐之力本身也需要遵守“一个专长只能选择一次”的规则限制。你不能在把雾隐之力转化为其它专长后，再次选择雾隐之力作为专长。
A40: 专精专注 | B40: 你非常擅长保持专注，获得以下好处： ·你在专注豁免上可以加上熟练加值。如果原本已经可以加上熟练加值，改为加上双倍的熟练加值。 ·当你因陷入失能而即将中断专注时，你可以令专注暂时不因失能而中断。在你的下个回合结束后，如果你依然处于失能状态，则专注中断。
A41: 威力攻击 | B41: 发动一次攻击检定之前，你可以让该次攻击检定承受-5减值。若命中，该次攻击的伤害掷骰获得等同于其基础伤害骰最大值的加值。举例来说，巨剑和灼热射线（2d6）额外造成12点伤害，长弓和11级武僧的徒手打击（1d8）额外造成8点伤害，魔能爆（1d10）额外造成10点伤害，长柄武器大师的附赠攻击和匕首（1d4）额外造成4点伤害。 焰舌、神圣武器、脆弱诅咒、精通至圣斩、超魔、战技、重击、偷袭等可能产生额外伤害骰的各种效果，都对威力攻击没有影响。
A42: 战士 | B42: 你接受了一定程度的军事训练，这给你带来以下好处： ·你获得一项军用武器熟练。 ·你从任意职业中选择并习得一项战斗风格。
A43: 巫师 | B43: 你接受了一定程度的魔法训练，这给你带来以下好处： ·你从“魔法伎俩”“奇术”“德鲁伊伎俩”“念合”中选择并习得一种戏法。 ·你从任意职业中选择并习得一种法术风格。
A44: 警觉 | B44: 经常对危机保持警惕，让你获得下列增益： ·你的先攻获得+5加值。 ·你在意识清醒时无法被突袭。 ·你看不到的生物对你发动攻击检定时，无法因此获得优势。
A45: 领袖之证 | B45: 先决条件：感知13 你可以花费10分钟来激励同伴，鼓舞他们战斗的信心。此时，你可以指定30尺内至多6名友方生物（可以包括你自己）作为目标。目标生物必须能够看见你或者能够听到你的声音的，且必须能够理解你。被指定的生物将因你获得临时生命值，其数值等于你的等级加上感知调整值。此后直至其完成一次短休或长休前，目标生物都无法再从该专长获益。 | K45: 骰子大小 | L45: 期望值 | M45: 最大值
A46: 语言学家 | B46: 你学习了不少语言和密码，获得下列增益： ·你的智力+1，不能超过24。 ·你习得三门自选语言，可以选择秘密语言。 ·你可以自创密码。而未经你传授解密方法的人只有两种方法可以破译你的密码：其一是进行智力检定（DC=你的智力值+熟练加值），或是以魔法破译。 | K46: d4 | L46: 2.5 | M46: 4
A47: 创生圣言 | B47: 先决条件：善良阵营 创生圣言是一种失落语言的遗存片段，被认为是宇宙诞生之初的回响，只有极少数的生物掌握了这种秘密语言。创生圣言没有书写形式，因为任何材料都无法承受它蕴含的神圣意义。 你习得“创生圣言”，并且学会了除了沟通以外的三种利用创生圣言的魔法，个人真名、崇高创造、天界咏唱，每种方法都需要透支生命。 个人真名 你可以尝试说出某个特定生物的个人真名（而非它的种族名），增强法术的约束力。在施法的同时，你支付等同于辨认怪物DC的生命值，进行一次辨认怪物检定，若检定成功，则说出了该生物的个人真名。 被说出个人真名的生物对抗传送、位面旅行、支配、异界誓缚的豁免具有劣势。当你施展一个使自身变形的法术时，如果你说出了某个特定生物的个人真名，你可以变形为它（而非它的种族中的一般个体）。 崇高创造 当你用手艺或魔法创造一个物件时，你观想了宇宙诞生的场景，支付一定的生命值，让物件的结构变得更加纯粹而完美。为无价值、非卖品或不超过100gp的物件，你需要支付10点生命值；物件的价值每乘10倍，你需要再支付10点生命值。你以此法创造的物件的AC增加等同于你的熟练加值的数值。你为创造物件所做的属性检定具有优势。 天界咏唱 创生圣言可以编入歌曲之中，成为超越凡间所有旋律，且回响着天堂之和谐的音乐。你可以在“吟唱”的同时，支付生命值来增幅一部分吟唱方式的效果，详见下表。 | K47: d6 | L47: 3.5 | M47: 6
A48: 毁灭真言 | B48: 先决条件：邪恶阵营 毁灭真言是一种尚未诞生的语言的预兆片段，被认为是宇宙寂灭之末的哀泣，只有极少数的生物掌握了这种秘密语言。毁灭真言没有书写形式，因为任何材料都无法承受它蕴含的亵渎意义。 你习得“毁灭真言”，并且学会了除了沟通以外的三种利用毁灭真言的魔法，凌人之令、衰败毁灭、渎神祈唤，每种方法都需要透支生命。 凌人之令 你说出某种“智力不大于8、等级不大于你”的生物的种族名，支配附近生物为你效力。使用一个动作，你支付等同于辨认怪物DC的生命值，进行一次辨认怪物检定，若检定成功，则附近30尺内的该种生物受你支配，持续1分钟；若检定失败，则目标在接下来的24小时内免疫你的凌人之令。 被支配的生物可以在每个自己的回合结束时进行一次感知豁免（DC=成功支配它的那次辨认怪物检定结果），豁免成功则不再受到支配，在接下来的24小时内免疫你的凌人之令。 衰败毁灭 当你对一个物件造成伤害时，或是尝试开锁、挣脱、破坏物件时，你观想了宇宙寂灭的场景，支付一定的生命值，让物件的结构变得更加脆弱而腐朽。为无价值、非卖品或不超过100gp的物件，你需要支付10点生命值；物件的价值每乘10倍，你需要再支付10点生命值。你对该物件造成的伤害可以无视其伤害阈值，你为开锁、挣脱、破坏此物件所做的属性检定具有优势。持续1分钟。 渎神祈唤 毁灭真言可以编入祈唤之中，成为超越凡间所有颂词，且暗示着炼狱之杀伐的咒语。你可以在获得“魔能祈唤”的同时，让自己的最大生命降低若干点，增幅一部分魔能祈唤的效果，详见下表。这种最大生命值的减损，无法被免疫或移除，除非你更换了被增幅的魔能祈唤。 | K48: d8 | L48: 4.5 | M48: 8
A49: 幸运 | B49: 你的离奇运气让你可以在最危险的时刻化险为夷。 你获得3点幸运点。当你进行攻击检定、属性检定、豁免检定时，你可以花费1幸运点，重骰其中一枚d20。你也可以在被攻击时选择花费1点幸运点，让攻击者重骰其中一枚d20。 若不止一个生物决定花费幸运点影响同一个骰值，则幸运点互相抵消，即并不会有重骰d20的行为。 完成一次长休后你可以恢复所有的幸运点。 | K49: d10 | L49: 5.5 | M49: 10
A50: 灵活移动 | B50: 你十分灵敏而快速。你获得下列增益： ·移动速度+10尺。 ·在困难地形的移动不再消耗额外的移动力。处于水下不会对你的移动和攻击产生任何惩罚。 ·对一个生物发动近战攻击后，无论命中与否，本回合剩下时间里你的主动移动都不会引发该生物的借机攻击。 | K50: d12 | L50: 6.5 | M50: 12
A51: 骑乘战斗 | B51: 骑乘时的你就像一头怪兽。当正在骑乘且未处于失能状态时，你获得下列增益： ·你对比你的坐骑体型更小的未骑乘生物发动近战攻击时，所进行的攻击检定具有优势。 ·如果一次攻击可以同时对你和你的坐骑具有效果线，那么当敌人对你的坐骑发动攻击检定时，你可以强迫该次攻击转而针对你自己。 ·你的坐骑获得“反射闪避”特性。 反射闪避 你在成为某一范围效应影响对象时，若该效应允许你通过成功的敏捷豁免来使伤害减半，则你在该豁免成功时不受伤害，而豁免失败时只受一半伤害。
A52: 奋力冲刺 | B52: 先决条件：骑乘战斗 当你以攻击动作执行“骑乘冲刺”时，如果你拥有在一个攻击动作内发动多次攻击的能力，那么你可以发动等量次数的攻击。目标只对你发动的第一次攻击造成的穿刺伤害具有易伤。
A53: 健壮 | B53: 你的生命上限增加等同于角色等级两倍的数值。
A54: 坚地之心 | B54: 先决条件：没有或拥有“反射闪避”特性 如果你没有“反射闪避”特性，那么你获得以下效果： 你在成为某一范围效应影响对象时，若该效应允许你通过成功的豁免来使伤害减半，则你在该豁免成功时不受伤害。 如果你拥有“反射闪避”特性，那么你获得以下效果： 你在成为某一范围效应影响对象时，若该效应允许你通过成功的豁免来使伤害减半，则你在该豁免成功时不受伤害，而豁免失败时只受一半伤害。
A55: 奇境触碰 | B55: 暴露在童话世界的魔法之下的经历已经改变了你，使你获得以下增益： ·你的体型增大一级或减小一级，由你在获得该专长时选择。 ·（仅限增大）你的生命上限增加等同于角色等级的数值。 ·（仅限减小）你的AC和敏捷豁免获得+1加值，你使用远程武器或带灵巧属性的武器进行攻击时的攻击检定和伤害掷骰获得+1加值。
A56: 精类触碰 | B56: 暴露在妖精荒野的魔法之下的经历已经改变了你，使你获得了以下增益： ·智力或感知+1，不能超过24。 ·你习得“迷踪步”以及一个由你选择的一环法术。该一环法术必须是预言系或者附魔系法术。你可以在不消耗法术位的情况下施展这些法术各一次。当你以此法施展某个法术后，你不能再次以此法施展该法术，直至你完成一次长休。这些法术的施法关键属性是你由此专长提升的属性。
A57: 影界触碰 | B57: 暴露在堕影冥界的魔法之下的经历已经改变了你，使你获得了以下增益： ·智力或感知+1，不能超过24。 ·你习得“隐形术”以及一个由你选择的一环法术。该一环法术必须是幻术系或死灵系法术。你可以在不消耗法术位的情况下施展这些法术各一次。当你以此法施展某个法术后，你不能再次以此法施展该法术，直至你完成一次长休。这些法术的施法关键属性是你由此专长提升的属性。
A58: 念动力 | B58: 你习得用你的意念移动物体的能力。你获得以下好处： ·智力或感知+1，不能超过24。 ·你习得“法师之手”戏法，你施展它无需言语和材料成分，并且你可以让该幽灵手隐形。如果你已经习得该戏法，你施展该戏法时其施法距离提升30尺。该戏法的施法关键属性是你由此专长提升的属性。 ·以一个附赠动作，你可以尝试以念动力推撞30尺内的一个你可见的生物。当你这样做时，目标必须成功通过一次力量豁免（DC=8+熟练加值+你由此专长提升的属性的属性调整值）否则将被你拉近或推离五尺。
A59: 心电感应 | B59: 你觉醒了用意念与其他生物交流的能力。你获得以下好处： ·智力或感知+1，不能超过24。 ·你可以和60尺内任何你可见的生物用心灵感应进行交流。你的心电沟通以一种你已知的语言的形式进行，该生物必须懂得该语言才能理解你。你的主动沟通并未给予该生物以心灵感应的形式回复你的能力。 ·你可以施展“侦测思想”法术，无需法术位和构材。以此法施法后，你在完成一次长休前不能再这样做。该法术的施法关键属性是你由此专长提升的属性。如果你拥有二环或更高的法术位，你可以消耗这些法术位施展该法术。
A60: 异种龙纹 | B60: 先决条件：出生于艾伯伦，没有其它龙纹。 你显现出异种龙纹。请设定它的外观和它造成的缺陷。你获得以下好处： ·体质+1，不能超过24。 ·你从法师法术列表中习得一个戏法。然后，从法师法术列表中选择一个1环法术，不能选择“获得魔宠”。你习得该法术，并能通过龙纹施展它。当你施展过一次此法术后，必须经过一次短休或长休才能再次通过龙纹施展。在施展这些法术时，体质是你的施法关键属性。 ·当你通过龙纹施展那个一环法术时，你能消耗一个生命骰并掷骰。如果掷骰结果是偶数，你将获得等同掷骰结果的临时生命值。如果掷骰结果是奇数，距离你30尺内的一个随机生物（不包括你）受到等同掷骰结果的力场伤害。如果范围内没有其他生物，则你会受到该伤害。 拥有异种龙纹专长的角色有机会展现更大的力量。当你达到10级时，这个角色有10%的几率获得传奇恩惠。如果角色没有得到传奇恩惠，他在下次升级时仍有10%的机会获得。 如果角色得到了一个传奇恩惠，由DM来决定具体效果（不会获得这些传奇恩惠——次元旅行之恩惠、高等魔法之恩惠、不朽不灭之恩惠、法术召返之恩惠）。 该角色同时永久性地失去一个生命骰，其最大生命值相应地减少一个生命骰加上其体质调整值（最少减少1）。这一减少无法以任何方法解除。
A61: 魔法学徒 | B61: 指定一个职业：吟游诗人、牧师、德鲁伊、契术师、法师、灵能师。你从指定职业法术列表里习得两个戏法。此外，你从相同列表里选择习得一个1环法术。你在两次长休之间，可以无需消耗法术位，施展该法术一次。 这些法术的施法关键属性取决于你指定的职业。
A62: 法术对抗大师 | B62: 你获得智力（奥秘）、智力（宗教）、智力（灵能）的技能熟练项，如果已有熟练项则改为加上两倍。 你在解除检定中，可以加上你的熟练加值，如果已经可以加上熟练加值则改为加上两倍的熟练加值。
... A64: 法术射手 | B64: 先决条件：至少可以施展一个法术 你学会如何操控特定的法术进行攻击，并获得下列增益： ·智力或感知+1，不能超过24。 ·当你施展需要进行攻击检定的法术时，该法术的施法距离加倍。 ·远程法术攻击忽视半身掩护，并将四分之三掩护视为半身掩护。 ·习得一个需要进行攻击检定的戏法。从吟游诗人、牧师、德鲁伊、灵能师、契术师、法师中选择其一，并从其相应的法术列表里选择该戏法。你施展该戏法的施法关键属性取决于你选择的职业。
A65: 绝境一搏 | B65: 骰先攻时，如果敌方生物的熟练加值总和，至少为友方生物的熟练加值总和的两倍，你立即获得并执行一个回合。 | S65: 力量值 | T65: 1 | U65: 2 | V65: 3 | W65: 4 | X65: 5 | Y65: 6 | Z65: 7 | AA65: 8 | AB65: 9 | AC65: 10 | AD65: 11 | AE65: 12 | AF65: 13 | AG65: 14 | AH65: 15 | AI65: 16 | AJ65: 17 | AK65: 18 | AL65: 19 | AM65: 20 | AN65: 21 | AO65: 22 | AP65: 23 | AQ65: 24 | AR65: 25 | AS65: 26 | AT65: 27 | AU65: 28 | AV65: 29 | AW65: 30
A66: 金属龙赋礼 | B66: 你掌握了一些金属龙的力量，你获得以下好处： ·龙类治疗。你习得“疗伤术”法术。你可以施展一次该法术而无需消耗法术位。当你以此法施展该法术后，你不能再次通过该特性施展它，直至你完成一次长休。该法术的施法关键属性是智力或感知（你在获得此专长时进行选择）。 ·庇护之翼。你可以展现出庇护之翼，保护你或者其他人免受攻击。在你或5尺内你可见的其他生物被一次攻击命中时，你可以使用你的反应来在你背后暂时显现出虚幻的翅膀。你使目标对抗该次攻击的AC获得加值，数值等同于你的熟练加值，此举可能导致该攻击丢失。你可以使用此反应等同于熟练加值的次数，在完成一次长休后恢复所有次数。 | S66: 微型 | T66: 7 | U66: 15 | V66: 22 | W66: 30 | X66: 37 | Y66: 45 | Z66: 52 | AA66: 60 | AB66: 67 | AC66: 75 | AD66: 82 | AE66: 90 | AF66: 97 | AG66: 105 | AH66: 115 | AI66: 125 | AJ66: 135 | AK66: 145 | AL66: 160 | AM66: 175 | AN66: 190 | AO66: 210 | AP66: 230 | AQ66: 275 | AR66: 275 | AS66: 300 | AT66: 325 | AU66: 375 | AV66: 425 | AW66: 500
A67: 色彩龙赋礼 | B67: 你掌握了一些色彩龙的力量，你获得以下好处： ·繁彩注魔。以一个附赠动作，你可以触碰一把简易武器或军用武器，向它注入以下能量之一：强酸，寒冷，火焰，闪电或毒素。在之后一分钟内，该武器在命中时额外造成1d4你所选伤害类型的伤害。使用此特性后，你在完成一次长休前不能再次使用。 ·反应抗性。当你受到强酸，寒冷，火焰，闪电或毒素伤害时，你可以使用你的反应，使自己在当此伤害中获得对应伤害类型的抗性。你可以使用该特性等同于你熟练加值的次数，你在完成一次长休后重获所有已使用的次数。 | S67: 小型 | T67: 11 | U67: 22 | V67: 33 | W67: 45 | X67: 56 | Y67: 67 | Z67: 78 | AA67: 90 | AB67: 101 | AC67: 112 | AD67: 123 | AE67: 135 | AF67: 146 | AG67: 157 | AH67: 172 | AI67: 187 | AJ67: 202 | AK67: 217 | AL67: 240 | AM67: 262 | AN67: 285 | AO67: 315 | AP67: 345 | AQ67: 375 | AR67: 412 | AS67: 450 | AT67: 487 | AU67: 562 | AV67: 637 | AW67: 750
A68: 穿刺者 | B68: 你已经可以在战斗中造成精准的穿刺。你获得以下好处： ·力量或敏捷+1，不能超过24。 ·每回合一次，当你用造成穿刺伤害的攻击命中一个生物时，你可以重投其中一个伤害骰。你必须使用重投的结果。 ·当你用造成穿刺伤害的攻击命中一个生物并且造成重击时，你可以在计算穿刺伤害时投一个额外的伤害骰。 | S68: 中型 | T68: 15 | U68: 30 | V68: 45 | W68: 60 | X68: 75 | Y68: 90 | Z68: 105 | AA68: 120 | AB68: 135 | AC68: 150 | AD68: 165 | AE68: 180 | AF68: 195 | AG68: 210 | AH68: 230 | AI68: 250 | AJ68: 270 | AK68: 290 | AL68: 320 | AM68: 350 | AN68: 380 | AO68: 420 | AP68: 500 | AQ68: 500 | AR68: 550 | AS68: 600 | AT68: 650 | AU68: 750 | AV68: 850 | AW68: 1000
A69: 挥砍者 | B69: 你已熟知该砍向何处以造成最重的伤害。你获得以下好处： ·力量或敏捷+1，不能超过24。 ·每回合一次，当你用造成挥砍伤害的攻击命中一个生物时，你可以使其速度降低10尺，直到你的下回合开始。 ·当你用造成挥砍伤害的攻击命中一个生物并造成重击时，你将其重伤，使其所作的攻击检定具有劣势，直至你的下回合开始。 | S69: 大型 | T69: 30 | U69: 60 | V69: 90 | W69: 120 | X69: 150 | Y69: 180 | Z69: 210 | AA69: 240 | AB69: 270 | AC69: 300 | AD69: 330 | AE69: 360 | AF69: 390 | AG69: 420 | AH69: 460 | AI69: 500 | AJ69: 540 | AK69: 580 | AL69: 640 | AM69: 700 | AN69: 760 | AO69: 840 | AP69: 1000 | AQ69: 1000 | AR69: 1100 | AS69: 1200 | AT69: 1300 | AU69: 1500 | AV69: 1700 | AW69: 2000
A70: 钝击者 | B70: 你擅长于碾碎敌人的技艺，你获得了以下增益： ·力量或体质+1，不能超过24。 ·每回合一次，当你用造成钝击伤害的攻击命中一个生物时，只要目标的体型并未比你大一级以上，你就可以将目标移动五尺至一个未被占据的空间。 ·当你用造成钝击伤害的攻击命中一个生物并造成重击时，直至你的下一回合开始，所有针对该生物的攻击检定具有优势。 | S70: 巨型 | T70: 60 | U70: 120 | V70: 180 | W70: 240 | X70: 300 | Y70: 360 | Z70: 420 | AA70: 480 | AB70: 540 | AC70: 600 | AD70: 660 | AE70: 720 | AF70: 780 | AG70: 840 | AH70: 920 | AI70: 1000 | AJ70: 1080 | AK70: 1160 | AL70: 1280 | AM70: 1400 | AN70: 1520 | AO70: 1680 | AP70: 2000 | AQ70: 2000 | AR70: 2200 | AS70: 2400 | AT70: 2600 | AU70: 3000 | AV70: 3400 | AW70: 4000
A71: 重击大师 | B71: 经过战斗训练，你越来越擅长寻找敌人的弱点，将重击视作自己理所当然的能力。你的攻击检定的重击范围+1，并从以下好处中选择一种获得： ·你造成重击后，可以不消耗移动力，移动最多10尺，作为同一次攻击的一部分。 ·你造成重击后，可以获得等同于1d10+攻击属性的属性调整值的临时生命值。 ·你造成重击的攻击可以无视目标的伤害抗性。 ·你以重击将一个敌对生物的生命值降至0时，你附近10尺内的所有敌对生物会陷入恐慌状态，直到你的下个回合结束。 你可以重复多次选择该专长，但每次都必须选择一种不同的好处。 | S71: 超巨型 | T71: 120 | U71: 240 | V71: 360 | W71: 480 | X71: 600 | Y71: 720 | Z71: 840 | AA71: 960 | AB71: 1080 | AC71: 1200 | AD71: 1320 | AE71: 1440 | AF71: 1560 | AG71: 1680 | AH71: 1840 | AI71: 2000 | AJ71: 2160 | AK71: 2320 | AL71: 2560 | AM71: 2800 | AN71: 3040 | AO71: 3360 | AP71: 4000 | AQ71: 4000 | AR71: 4400 | AS71: 4800 | AT71: 5200 | AU71: 6000 | AV71: 6800 | AW71: 8000
A72: 近程射手 | B72: 你能够在近距离保持射击的精准性和协调性。 你在敌方生物的触及范围内发动远程攻击时，不会因此受到借机攻击，攻击也不会因此具有劣势。
A73: 凶蛮打手 | B73: 你的酒馆斗殴经验，带给你以下好处： ·力量或体质+1，不能超过24。 ·每回合一次，在掷近战武器攻击的伤害骰时，你可以重掷武器的伤害骰并选用新旧骰值二者之一。 | S73: 负重 | T73: =VLOOKUP(角色!M6,S65:AW71,1+主要情况!D5,0)*IF(装备!G27="是有力体型",2,1) -> #N/A
A74: 战地施法者 | B74: 先决条件：至少可以施展一个法术 你学会如何在混乱的战场上施展法术，并获得下列增益： ·你的专注豁免具有优势。 ·你在持握武器和盾牌时依然可以满足施法所需的姿势成分。 ·当敌方生物引发你的借机攻击时，如果该生物处于你的施法距离为触及的法术的施法距离内，你可以对该生物施展一个目标型法术作为借机攻击。该法术不一定要是施法距离为触及的法术，但是施法时间必须是1动作，且该生物必须为法术的唯一目标。
A75: 战斗反射 | B75: 先决条件：敏捷13 你在每一轮中（从你的当前回合开始，到你的下个回合开始），发动的前X次借机攻击无需消耗反应，X等于敏捷调整值。如果你处于无法执行反应的状态（例如失能、被“电爪”命中），那么你依然不能发动借机攻击。 敌对生物主动移动进入你周围5尺时，会引发你的借机攻击。
A76: 巫师杀手 | B76: 你拥有一套对付施法者的近身战法，并获得下列增益： ·你的触及范围内的一个生物施展法术时，你可以用你的反应对该生物发动一次借机攻击。你自由决定这次借机攻击发生在施法之前还是之后。 ·生物受到由你造成的伤害时，对抗该次伤害进行的专注豁免具有劣势。 ·你为抵抗触及范围内生物对你施展的法术进行的豁免具有优势。
A77: 精通巫师杀手 | B77: 先决条件：巫师杀手 你对付施法者的近身战法得到了进一步增强： ·当你通过“巫师杀手”，选择在触及范围内的生物施法之前对它发动一次借机攻击，该次借机攻击命中后，施法者需要进行一次专注豁免，豁免DC取决于该次借机攻击的伤害。豁免失败则法术被反制。 ·你为抵抗一个法术进行豁免时，如果施法者处于你的触及范围内，你视为具有该次豁免的熟练项。
A78: 剑刃丛生 | B78: 先决条件：战斗反射，敏捷13 你保持着谨慎的防御，寻找着对手每一个可能的破绽，即使是最细微的移动也可能成为你反击的契机。获得以下增益： ·你忽视其它生物的“移动时不会引发借机攻击”的特性，例如撤离动作和飞掠特性。 ·你触及范围内的生物进行传送之前，你可以对它发动借机攻击。 ·敌对生物传送进入你的触及范围之后，你可以对它发动借机攻击。
A79: 哨兵 | B79: 你的掌握的技术让你在击破敌人防御时占尽优势，并获得下列增益： ·你的借机攻击命中目标时，目标在本回合剩下时间内的移动速度降至0，并处于锚定状态。 ·处于你触及范围内的生物对除你外的目标发动攻击后，你可以对攻击者发动一次借机攻击。
A80: 超自然直觉 | B80: 你对超凡生物的行动有了更敏锐的感应和克制： 当一个生物在你的触及范围内，使用动作、附赠动作、反应、传奇动作，启动一种“非法术的魔法效应”或“吐息武器”时，你可以对它发动借机攻击。若该次借机攻击命中，目标在1分钟内，无法再次启动与引发借机攻击的那次“非法术的魔法效应”或“吐息武器”同名的能力。
A81: 灵动借机 | B81: 先决条件：战斗反射，敏捷13 你时刻准备着面对意外状况。获得以下增益： ·发动的借机攻击具有优势。 ·每次发动借机攻击后，你可以移动5尺，作为同一个行动的一部分。
A82: 战技借机 | B82: 先决条件：任意战技专长 你对打击技相当熟练，能够在纷乱战场上趁机发动出来。 当敌方生物引发你的借机攻击时，你可以对该生物使用一个打击技作为借机攻击。该打击技的启动时间必须是一动作或是替换一次攻击，且该生物必须为该打击技的唯一目标。 如果作为借机攻击的打击技命中了目标，那么在你的下个回合内，你对目标使用的任意打击技的卓越骰消耗降低1枚。该生物不一定要是这些打击技的唯一目标，但至少要是目标之一。
A83: 罗比拉战术 | B83: 先决条件：9级，战斗反射，敏捷13 使用罗比拉战术战术时，你承受伤害以将你置于更有利的形势。此危险的牺牲并非不适或不智的，但失败的报复攻击会使优势丧失。罗比拉男爵，一个轻率又鲁莽的战士，以此技巧对抗敌人而闻名。在你开始行动时，你可以采取会使你受伤的战斗姿势，但让你能在对手攻击你时，看到他们防御的破绽。 任何一位攻击你的敌人，命中后的伤害掷骰可以加上他们的熟练加值。然而在他们攻击你之后，无论是否命中，只要他们在你的触及范围内，你就可以对他们发动借机攻击。
A84: 双武器低级战士 | B84: 先决条件：两只手，敏捷15 你使用以下规则进行双持武器战斗，取代“战斗-发动攻击-近战攻击-双持武器战斗”一节原有的规则： 如果你的双手分别持握了一把轻型近战武器，那么当你在自己的回合内执行攻击动作时，你可以选择一只手作为主手，仅使用主手武器发动攻击。然后你会获得一个额外的附赠动作，该附赠动作的唯一用途是让你以另外一只手作为副手，发动一次具有劣势的武器攻击。该附赠攻击的伤害不获得你的属性调整值加成，除非该调整值为负数。
A85: 双武器中级战士 | B85: 先决条件：双武器低级战士，敏捷17，额外攻击 进行双持武器战斗时，你可以用附赠动作以副手发动两次具有劣势的武器攻击。
A86: 二刀流 | B86: 先决条件：双武器低级战士 你可以使用一把不具有轻型属性的单手近战武器作为主手武器、和一把轻型近战武器作为副手武器，进行双持武器战斗。 你用附赠动作以副手发动的前两次攻击，不会因双持而具有劣势。 | L86: 无机素材 | M86: 有机素材 | N86: 魔晶素材 | O86: 工艺费用 | Q86: 生物类型 | R86: 无机素材系数 | S86: 有机素材系数 | T86: 魔晶素材系数
A87: 双武器高级战士 | B87: 先决条件：双武器中级战士，敏捷19，精通额外攻击 进行双持武器战斗时，你可以用附赠动作以副手发动三次具有劣势的武器攻击。 | K87: 魔药 | L87: 1 | M87: 3 | N87: 4 | O87: 20 | Q87: 异怪 | R87: 0.3 | S87: 0.4 | T87: 0.6
A88: 双武器超级战士 | B88: 先决条件：双武器高级战士，敏捷21，非凡额外攻击 进行双持武器战斗时，你可以用附赠动作以副手发动四次具有劣势的武器攻击。 | K88: 卷轴 | L88: 0 | M88: 3 | N88: 5 | O88: 20 | Q88: 野兽 | R88: 0 | S88: 0.5 | T88: 0
A89: 绝对双刃 | B89: 先决条件：二刀流，双武器高级战士 你可以使用两把不具有轻型属性的单手近战武器，进行双持武器战斗。 你用附赠动作以副手发动的前四次攻击，不会因双持而具有劣势。 | K89: 法器 | L89: 1 | M89: 1 | N89: 6 | O89: 20 | Q89: 植物 | R89: 0 | S89: 0.7 | T89: 0.3
A90: 双刀借机 | B90: 先决条件：双武器中级战士 进行双持武器战斗时，当敌方生物引发你的借机攻击，你可以对该生物分别以主手武器和副手武器发动一次攻击，作为借机攻击。 | K90: 武器 | L90: 3 | M90: 3 | N90: 2 | O90: 20 | Q90: 天界生物 | R90: 0.2 | S90: 0.6 | T90: 0.7
A91: 团队防御 | B91: 你无法获得伤害抗性、免疫、吸收。 每当一种效应使你获得伤害抗性、免疫、吸收时，改为在该效应的持续时间内，你在未失能时散发着半径10尺的保护灵光，这是一种魔法性的蓝色光辉。灵光范围内除你以外的友方生物获得对应的伤害抗性、免疫、吸收。 | K91: 护甲（布甲、皮甲、镶钉皮甲、蛛丝衣、藤甲、金竹甲、龙龟铠、木制盾牌） | L91: 1 | M91: 6 | N91: 1 | O91: 20 | Q91: 构装生物 | R91: 1.2 | S91: 0 | T91: 0.3
A92: 灵魂装备 | B92: 魂能是一种由所有活着的、死去的、甚至在理论上还包括还未出生的智能生物的灵魂能量构成的不定形的魔法物质。在它最纯粹的形态下，魂能表现为一种闪着深蓝色的光芒的迷雾。受过特定训练或者有特殊天赋的人可以将魂能塑造成具有物理形态的实体，也就是灵魂装备。 你觉醒了塑造灵魂装备的魂能魔法天赋，可以在自己的身体部位上创造出一件由你选择的魔法服饰，详见“装备-魔法物品-服饰”。当你升级后，你可以重新选择这件魔法服饰的品类。如果你消耗了一件灵魂装备的魔力，而该种魔力不可再生，那么即使升级也无法重新塑造新的灵魂装备。举例来说，塑造“杂货法袍”并从其中的补丁获取物品后，你不能把二手的杂货法袍换成其它服饰。 灵魂装备无法从你身上卸除，但你可以用一个动作让其消失或重现。当你死亡时，它会随之消失；当你复活时，它会随之重现。如果灵魂装备需要同调，只要你能够满足同调条件，你就可以无需同调位去同调它。如果灵魂装备被摧毁，在你完成一次短休或长休后，它会重现。 你能以此法创造出的服饰的最大价值，取决于你的等级，以及该服饰是否需要同调，详见下表。下表中超过20级的部分是为高等级怪物准备的，玩家角色通常无法获得。 你可以多次选择该专长，每次塑造一件不同部位的灵魂装备。 | K92: 护甲（链甲衫、鳞甲、半身板甲、链甲、板条甲、板甲、金属盾牌） | L92: 6 | M92: 1 | N92: 1 | O92: 20 | Q92: 不死生物 | R92: 0.2 | S92: 0.3 | T92: 0.2
A93: 演员 | B93: 精通于模仿和演戏，让你获得下列增益： ·智力+1，不能超过24。 ·当你试图将自己扮演成另一个人时，你进行感知（欺瞒）和智力（表演）检定具有优势。 ·你可以模仿另一个生物的说话口吻和声音。前提是你必须听过被模仿者至少1分钟的说话或发声。对方聆听你的模仿时可以进行一次感知（洞悉）检定，并与你的感知（欺瞒）检定进行对抗，若对方胜出便会意识到声音是模仿出来的。 | K93: 服饰（手套、护腿、斗篷、外套、帽子、鞋子） | L93: 2 | M93: 4 | N93: 2 | O93: 20 | Q93: 龙类 | R93: 0.5 | S93: 1 | T93: 1
A94: 敏锐心灵 | B94: 你可以单单依靠心算来记录时间和方向的变换，并且可以做到精确无比。你获得下列增益： ·智力+1，不能超过24。 ·你始终知道北边的方位。 ·你始终知道距离下一次日出或日落还有多久。 ·你可以完美复述出一个月内你所听到或看到的任何事。 | K94: 服饰（护符、腰带、头饰、眼镜、项链、戒指） | L94: 4 | M94: 2 | N94: 2 | O94: 20 | Q94: 元素生物 | R94: 0.7 | S94: 0 | T94: 0.3
A95: 观察力 | B95: 你能够迅速把握周遭环境的要点，并获得下列增益： ·智力或感知+1，不能超过24。 ·某生物在讲话时，若你可以看见目标的嘴且你可以理解其语言，则你就可以依靠读唇来解读目标正在讲什么。 ·你的被动感知（察觉）值和被动智力（调查）值获得+5加值。 | K95: 奇物 | L95: 3 | M95: 1 | N95: 4 | O95: 20 | Q95: 精类 | R95: 0.4 | S95: 0.3 | T95: 0.3
A96: 历史正文 | B96: 先决条件：智力19 你对战争的把控超越了空间，开始防范时间维度的打击。 当过去的历史被某人篡改，危及到你当下的存在性时，你可以用意念（无需任何动作）发动历史正文。在篡改者面前，创造出具有你当下的全部数据和装备的复制体。你可以在发动历史正文时，选择身边30尺内若干名自愿生物，也创造出它们的复制体，作为维护历史的帮手。 这些复制体的唯一目的是保护既定的历史，确保你可以继续存在，不会做出其它行动。当篡改者被阻止时，复制体也就完成了使命，随后消失。 举例来说，你的仇敌回到了三十年前，试图消灭婴儿时期的你。此时，保卫历史的复制体便能够出现，尽力与这名仇敌作战，或是带着婴儿时期的你逃走，或是尝试找到婴儿时期的仇敌将它杀害。 | K96: 攻城装置 | L96: 6 | M96: 2 | N96: 0 | O96: 20 | Q96: 邪魔 | R96: 0.2 | S96: 0.6 | T96: 0.7
A97: 强健身心 | B97: 选择一或两种属性，并获得下列增益： ·获得所选属性的豁免熟练项。 ·如果你仅选择了一种属性，则该属性+1，不能超过24。 你可以多次选择该专长，每次选择之前未选择过的属性。 | K97: 载具 | L97: 5 | M97: 3 | N97: 0 | O97: 20 | Q97: 巨人 | R97: 0.3 | S97: 0.6 | T97: 0.3
A98: 圣斗士顽强 | B98: 先决条件：强健身心 同样的招式，对你难以生效第二次。 为抵抗某种效应进行豁免时，你在过去的1分钟内，每因为同名效应进行过一次豁免，在该次豁免中便有一重优势。 没有特定效应名称的豁免，例如濒死豁免、受到伤害后的专注豁免，无法享受该专长的增益。 | Q98: 类人生物 | R98: 0 | S98: 0.6 | T98: 0.2
A99: 危机管理 | B99: 先决条件：强健身心 遇到危险时，你能够做出应对，减少自己承受的损失。 如果你拥有力量豁免熟练项：敌方生物使你陷入减速、倒地、束缚、锚定、缚地状态之前，你可以立即移动“5×力量调整值”尺。你也可以消耗一个反应，改为移动等同于你的移动速度的距离。然后才陷入对应的状态。 如果你拥有敏捷豁免熟练项：你或其它友方生物使你获得加速、隐形、虚化状态之后，你可以立即执行一次撤离或躲藏（仍需满足躲藏的所有条件）。 如果你拥有体质豁免熟练项：当敌方生物使你陷入目盲、耳聋、力竭、中毒、衰老状态之后，在接下来的一分钟之内，你有两次机会，无视你在攻击检定、属性检定、豁免检定上的一项劣势。 如果你拥有智力豁免熟练项：敌方生物使你陷入恍惚、失能、麻痹、石化、震慑、昏迷（因生命值降为0而导致的昏迷除外）、睡眠之前，你可以立即施展一个施法时间为1动作的戏法。你也可以消耗一个反应，改为施展一个施法时间为1动作的法术。然后才陷入对应的状态。 如果你拥有感知豁免熟练项：敌方生物使你陷入魅惑、恐慌、支配、嗜血状态之前，你可以立即发动一次武器攻击。你也可以消耗一个反应，改为发动次数等同于你在攻击动作中的正常攻击次数的攻击。然后才陷入对应的状态。 | Q99: 怪兽 | R99: 0.4 | S99: 0.4 | T99: 0.4
A100: 适应性 | B100: 先决条件：强健身心 你适应了一些不利效果，让自己不至于陷入过于艰难的处境。 当你在对抗一次负面状态的豁免中失败，如果你的检定结果与豁免DC的差值不超过8点，那么你只会陷入对应负面状态的较弱版本。详见下表。 | Q100: 泥怪 | R100: 0.6 | S100: 0.4 | T100: 0.2
A101: 熟习 | B101: ·你的智力+1，不能超过24。 ·获得三种自选的技能熟练项。
A102: 技艺专家 | B102: 你已磨练了自身的特定技艺，并获得了以下好处： ·选择一项属性提升1，不能超过24。 ·你选择并获得一项技能的熟练项。 ·选择一项你熟练的技能，你获得该技能的专精。
A103: 动作如潮 | B103: 先决条件：战斗风格，一种军用武器熟练 你的回合内，你可以突破极限，以获取一个额外的动作、一个额外的附赠动作、等同于移动速度的移动力。 使用该特性后，你可以通过以下两种方式之一，来重获该特性的使用机会： 1、角色等级提升一级。 2、在当前等级完成10次长休。
A104: 武器大师 | B104: 经过大量练习后，你熟练的掌握了各种武器的使用方法，并获得下列增益： ·力量或敏捷+1，不能超过24。 ·获得简易武器和军用武器的熟练项。
...

Sheet 计算器
A1: 购点计算器 | F1: 属性提升 | M1: 物品素材计算器
B2: 属性值 | C2: 调整值 | D2: 花费点数 | G2: 购点/骰点值 | H2: 升级 | I2: 专长 | J2: 物品 | K2: 最终结果 | M2: 物品种类 | N2: 价格（gp） | O2: 无机素材（份） | P2: 有机素材（份） | Q2: 魔晶（份） | R2: 工艺费用（gp）
A3: 力量 | B3: 10 | C3: =INT(B3/2-5) -> 0 | D3: =VLOOKUP(B3,图表!T1:U10,2,FALSE) -> 2 | F3: 力量 | G3: =B3 -> 10 | K3: =SUM(G3:J3) -> 10 | M3: 服饰（手套、护腿、斗篷、外套、帽子、鞋子） | N3: 1000 | O3: =VLOOKUP(M3,图表!K86:N97,2,0)*N3/100 -> 20 | P3: =VLOOKUP(M3,图表!K86:N97,3,0)*N3/100 -> 40 | Q3: =VLOOKUP(M3,图表!K86:N97,4,0)*N3/100 -> 20 | R3: =N3*0.2 -> 200
A4: 敏捷 | B4: 15 | C4: =INT(B4/2-5) -> 2 | D4: =VLOOKUP(B4,图表!T1:U10,2,FALSE) -> 9 | F4: 敏捷 | G4: =B4 -> 15 | K4: =SUM(G4:J4) -> 15
A5: 体质 | B5: 15 | C5: =INT(B5/2-5) -> 2 | D5: =VLOOKUP(B5,图表!T1:U10,2,FALSE) -> 9 | F5: 体质 | G5: =B5 -> 15 | K5: =SUM(G5:J5) -> 15
A6: 智力 | B6: 10 | C6: =INT(B6/2-5) -> 0 | D6: =VLOOKUP(B6,图表!T1:U10,2,FALSE) -> 2 | F6: 智力 | G6: =B6 -> 10 | K6: =SUM(G6:J6) -> 10
A7: 感知 | B7: 15 | C7: =INT(B7/2-5) -> 2 | D7: =VLOOKUP(B7,图表!T1:U10,2,FALSE) -> 9 | F7: 感知 | G7: =B7 -> 15 | K7: =SUM(G7:J7) -> 15
M8: 怪物素材计算器
A9: 总和 | B9: =SUM(B3:B7) -> 65 | C9: =SUM(C3:C7) -> 6 | D9: =SUM(D3:D7) -> 31 | M9: 生物类型 | N9: 怪物等级 | O9: 怪物数量 | P9: 无机素材 | Q9: 有机素材 | R9: 魔晶
A10: 购点选项 | B10: 32 | C10: 购点法 | M10: 构装生物 | N10: 20 | O10: 1 | P10: =VLOOKUP(M10,图表!Q86:T100,2,0)*N10*N10*O10 -> 480 | Q10: =VLOOKUP(M10,图表!Q86:T100,3,0)*N10*N10*O10 -> 0 | R10: =VLOOKUP(M10,图表!Q86:T100,4,0)*N10*N10*O10 -> 120
A11: 剩余点数 | B11: =B10-D9 -> 1 | C11: 点 | F11: d20成功率计算器
G12: 优劣情况 | H12: 加值 | I12: 目标值 | J12: 达到目标的概率
F13: D20 | G13: 均势 | H13: 9 | I13: 20 | J13: =IF(G13="均势",G16,IF(G13="一重优势",1-G15*G15,IF(G13="两重优势",1-G15*G15*G15,IF(G13="一重劣势",G16*G16,IF(G13="两重劣势",G16*G16*G16,IF(G13="三重优势",1-G15*G15*G15*G15,G16*G16*G16*G16)))))) -> 0.5
F15: 均势失败率 | G15: =MAX(-0.05+(I13-H13)/20,0) -> 0.5 | M15: 伤害计算器
F16: 均势成功率 | G16: =MIN(1.05-(I13-H13)/20,1) -> 0.5 | N16: 骰子总数 | O16: 骰子面数
M17: 骰值伤害1 | N17: 2 | O17: d6 | Q17: 伤害期望（常规）
F18: 攻击命中率计算器 | M18: 骰值伤害2 | N18: 4 | O18: d4 | Q18: =N21+N17*VLOOKUP(O17,图表!K46:L50,2,0)+N18*VLOOKUP(O18,图表!K46:L50,2,0)+N19*VLOOKUP(O19,图表!K46:L50,2,0)+N20*VLOOKUP(O20,图表!K46:L50,2,0) -> 27
G19: 优劣情况 | H19: 加值 | I19: 目标AC | J19: 命中目标的概率 | M19: 骰值伤害3 | O19: d8 | Q19: 伤害期望（重击）
F20: D20 | G20: 一重优势 | H20: 3 | I20: 20 | J20: =IF(G20="均势",G23,IF(G20="一重优势",1-G22*G22,IF(G20="两重优势",1-G22*G22*G22,IF(G20="一重劣势",G23*G23,IF(G20="两重劣势",G23*G23*G23,IF(G20="三重优势",1-G22*G22*G22*G22,G23*G23*G23*G23)))))) -> 0.36 | M20: 骰值伤害4 | O20: d12 | Q20: =N21+2*N17*VLOOKUP(O17,图表!K46:L50,2,0)+2*N18*VLOOKUP(O18,图表!K46:L50,2,0)+2*N19*VLOOKUP(O19,图表!K46:L50,2,0)+2*N20*VLOOKUP(O20,图表!K46:L50,2,0) -> 44
F21: 重击范围 | G21: 2 | J21: 重击的概率 | M21: 固定值伤害 | N21: 10
F22: 均势失败率 | G22: =1-G23 -> 0.8 | J22: =IF(G20="均势",0.05*G21,IF(G20="一重优势",1-(1-0.05*G21)*(1-0.05*G21),IF(G20="两重优势",1-(1-0.05*G21)*(1-0.05*G21)*(1-0.05*G21),IF(G20="三重优势",1-(1-0.05*G21)*(1-0.05*G21)*(1-0.05*G21)*(1-0.05*G21),IF(G20="一重劣势",(0.05*G21)*(0.05*G21),IF(G20="两重劣势",(0.05*G21)*(0.05*G21)*(0.05*G21),(0.05*G21)*(0.05*G21)*(0.05*G21)*(0.05*G21))))))) -> 0.19
F23: 均势成功率 | G23: =MIN(MAX(MIN(1.05-(I20-H20)/20,1),G21*0.05),0.95) -> 0.2 | M23: 结合使用“攻击命中率计算器”和“伤害计算器”
M24: 计算命中率、重击率之后的单次攻击伤害期望 | P24: =Q18*(J20-J22)+Q20*J22 -> 12.95
